azlocal/__init__.py
azlocal/azdlocal.py
azlocal/azlocal.py
azlocal/constants.py
azlocal/funclocal.py
azlocal/shared.py
azlocal/tflocal.py
azlocal/python_local_sdk/__init__.py
azlocal/python_local_sdk/python_local_sdk.py
azlocal-0.0.16.dist-info/licenses/LICENSE
azlocal-0.0.16.dist-info/METADATA
azlocal-0.0.16.dist-info/WHEEL
azlocal-0.0.16.dist-info/entry_points.txt
azlocal-0.0.16.dist-info/top_level.txt
azlocal-0.0.16.dist-info/RECORD
